{
  "language": "Solidity",
  "sources": {
    "@openzeppelin/contracts/access/Ownable.sol": {
      "content": "// SPDX-License-Identifier: MIT\n// OpenZeppelin Contracts (last updated v5.0.0) (access/Ownable.sol)\n\npragma solidity ^0.8.20;\n\nimport {Context} from \"../utils/Context.sol\";\n\n/**\n * @dev Contract module which provides a basic access control mechanism, where\n * there is an account (an owner) that can be granted exclusive access to\n * specific functions.\n *\n * The initial owner is set to the address provided by the deployer. This can\n * later be changed with {transferOwnership}.\n *\n * This module is used through inheritance. It will make available the modifier\n * `onlyOwner`, which can be applied to your functions to restrict their use to\n * the owner.\n */\nabstract contract Ownable is Context {\n    address private _owner;\n\n    /**\n     * @dev The caller account is not authorized to perform an operation.\n     */\n    error OwnableUnauthorizedAccount(address account);\n\n    /**\n     * @dev The owner is not a valid owner account. (eg. `address(0)`)\n     */\n    error OwnableInvalidOwner(address owner);\n\n    event OwnershipTransferred(address indexed previousOwner, address indexed newOwner);\n\n    /**\n     * @dev Initializes the contract setting the address provided by the deployer as the initial owner.\n     */\n    constructor(address initialOwner) {\n        if (initialOwner == address(0)) {\n            revert OwnableInvalidOwner(address(0));\n        }\n        _transferOwnership(initialOwner);\n    }\n\n    /**\n     * @dev Throws if called by any account other than the owner.\n     */\n    modifier onlyOwner() {\n        _checkOwner();\n        _;\n    }\n\n    /**\n     * @dev Returns the address of the current owner.\n     */\n    function owner() public view virtual returns (address) {\n        return _owner;\n    }\n\n    /**\n     * @dev Throws if the sender is not the owner.\n     */\n    function _checkOwner() internal view virtual {\n        if (owner() != _msgSender()) {\n            revert OwnableUnauthorizedAccount(_msgSender());\n        }\n    }\n\n    /**\n     * @dev Leaves the contract without owner. It will not be possible to call\n     * `onlyOwner` functions. Can only be called by the current owner.\n     *\n     * NOTE: Renouncing ownership will leave the contract without an owner,\n     * thereby disabling any functionality that is only available to the owner.\n     */\n    function renounceOwnership() public virtual onlyOwner {\n        _transferOwnership(address(0));\n    }\n\n    /**\n     * @dev Transfers ownership of the contract to a new account (`newOwner`).\n     * Can only be called by the current owner.\n     */\n    function transferOwnership(address newOwner) public virtual onlyOwner {\n        if (newOwner == address(0)) {\n            revert OwnableInvalidOwner(address(0));\n        }\n        _transferOwnership(newOwner);\n    }\n\n    /**\n     * @dev Transfers ownership of the contract to a new account (`newOwner`).\n     * Internal function without access restriction.\n     */\n    function _transferOwnership(address newOwner) internal virtual {\n        address oldOwner = _owner;\n        _owner = newOwner;\n        emit OwnershipTransferred(oldOwner, newOwner);\n    }\n}\n"
    },
    "@openzeppelin/contracts/token/ERC20/IERC20.sol": {
      "content": "// SPDX-License-Identifier: MIT\n// OpenZeppelin Contracts (last updated v5.0.0) (token/ERC20/IERC20.sol)\n\npragma solidity ^0.8.20;\n\n/**\n * @dev Interface of the ERC20 standard as defined in the EIP.\n */\ninterface IERC20 {\n    /**\n     * @dev Emitted when `value` tokens are moved from one account (`from`) to\n     * another (`to`).\n     *\n     * Note that `value` may be zero.\n     */\n    event Transfer(address indexed from, address indexed to, uint256 value);\n\n    /**\n     * @dev Emitted when the allowance of a `spender` for an `owner` is set by\n     * a call to {approve}. `value` is the new allowance.\n     */\n    event Approval(address indexed owner, address indexed spender, uint256 value);\n\n    /**\n     * @dev Returns the value of tokens in existence.\n     */\n    function totalSupply() external view returns (uint256);\n\n    /**\n     * @dev Returns the value of tokens owned by `account`.\n     */\n    function balanceOf(address account) external view returns (uint256);\n\n    /**\n     * @dev Moves a `value` amount of tokens from the caller's account to `to`.\n     *\n     * Returns a boolean value indicating whether the operation succeeded.\n     *\n     * Emits a {Transfer} event.\n     */\n    function transfer(address to, uint256 value) external returns (bool);\n\n    /**\n     * @dev Returns the remaining number of tokens that `spender` will be\n     * allowed to spend on behalf of `owner` through {transferFrom}. This is\n     * zero by default.\n     *\n     * This value changes when {approve} or {transferFrom} are called.\n     */\n    function allowance(address owner, address spender) external view returns (uint256);\n\n    /**\n     * @dev Sets a `value` amount of tokens as the allowance of `spender` over the\n     * caller's tokens.\n     *\n     * Returns a boolean value indicating whether the operation succeeded.\n     *\n     * IMPORTANT: Beware that changing an allowance with this method brings the risk\n     * that someone may use both the old and the new allowance by unfortunate\n     * transaction ordering. One possible solution to mitigate this race\n     * condition is to first reduce the spender's allowance to 0 and set the\n     * desired value afterwards:\n     * https://github.com/ethereum/EIPs/issues/20#issuecomment-263524729\n     *\n     * Emits an {Approval} event.\n     */\n    function approve(address spender, uint256 value) external returns (bool);\n\n    /**\n     * @dev Moves a `value` amount of tokens from `from` to `to` using the\n     * allowance mechanism. `value` is then deducted from the caller's\n     * allowance.\n     *\n     * Returns a boolean value indicating whether the operation succeeded.\n     *\n     * Emits a {Transfer} event.\n     */\n    function transferFrom(address from, address to, uint256 value) external returns (bool);\n}\n"
    },
    "@openzeppelin/contracts/utils/Context.sol": {
      "content": "// SPDX-License-Identifier: MIT\n// OpenZeppelin Contracts (last updated v5.0.1) (utils/Context.sol)\n\npragma solidity ^0.8.20;\n\n/**\n * @dev Provides information about the current execution context, including the\n * sender of the transaction and its data. While these are generally available\n * via msg.sender and msg.data, they should not be accessed in such a direct\n * manner, since when dealing with meta-transactions the account sending and\n * paying for execution may not be the actual sender (as far as an application\n * is concerned).\n *\n * This contract is only required for intermediate, library-like contracts.\n */\nabstract contract Context {\n    function _msgSender() internal view virtual returns (address) {\n        return msg.sender;\n    }\n\n    function _msgData() internal view virtual returns (bytes calldata) {\n        return msg.data;\n    }\n\n    function _contextSuffixLength() internal view virtual returns (uint256) {\n        return 0;\n    }\n}\n"
    },
    "contracts/v2/interfaces/IGateway.sol": {
      "content": "// SPDX-License-Identifier: MIT\npragma solidity ^0.8.30;\n\nimport { ProtocolTypes } from \"./ProtocolTypes.sol\";\n\ninterface IGateway {\n    function processLendingInstruction(\n        ProtocolTypes.Output[] calldata inputs,\n        bytes calldata data\n    ) external returns (ProtocolTypes.Output[] memory outputs);\n\n    /// @notice Return user-side authorization calls for the given lending instructions.\n    ///         One element per input (or (address(0), bytes(\"\")) if none needed).\n    ///         Also returns the produced outputs from the simulation of these instructions.\n    function authorize(\n        ProtocolTypes.LendingInstruction[] calldata instrs,\n        address caller,\n        ProtocolTypes.Output[] calldata inputs\n    ) external view returns (address[] memory targets, bytes[] memory data, ProtocolTypes.Output[] memory produced);\n\n    /// @notice Return user-side deauthorization calls for the given lending instructions.\n    ///         Used to revoke permissions after execution.\n    function deauthorize(\n        ProtocolTypes.LendingInstruction[] calldata instrs,\n        address caller,\n        ProtocolTypes.Output[] calldata inputs\n    ) external view returns (address[] memory targets, bytes[] memory data);\n}\n"
    },
    "contracts/v2/interfaces/ProtocolTypes.sol": {
      "content": "// SPDX-License-Identifier: MIT\npragma solidity ^0.8.30;\n\nlibrary ProtocolTypes {\n    struct ProtocolInstruction {\n        string protocolName;\n        bytes data;\n    }\n\n    struct Output {\n        address token;\n        uint256 amount;\n    }\n\n    // Common lending instruction schema for gateways (deposit/withdraw/borrow/repay)\n    enum LendingOp {\n        Deposit,\n        DepositCollateral,\n        WithdrawCollateral,\n        Borrow,\n        Repay,\n        GetBorrowBalance,\n        GetSupplyBalance,\n        Swap,\n        SwapExactOut,\n        SetEMode  // Aave V3 E-Mode: amount encodes categoryId (0 = disable E-Mode)\n    }\n    struct InputPtr {\n        uint256 index;\n    }\n    /**\n     * Cross-protocol instruction.\n     * - For Compound you can pass `context = abi.encode(address marketBaseToken)`\n     *   which tells the gateway which Comet (market) to use. Empty means infer from token.\n     */\n    struct LendingInstruction {\n        LendingOp op;\n        address token; // underlying being acted on (base or collateral)\n        address user; // end user on whose account we operate\n        uint256 amount; // amount in underlying units\n        bytes context; // (optional) protocol-specific blob (e.g., Compound marketBaseToken)\n        InputPtr input; // (optional) pointer to prior output (UTXO); use if index < inputs.length\n    }\n}\n"
    },
    "contracts/v2/KapanAuthorizationHelper.sol": {
      "content": "// SPDX-License-Identifier: MIT\npragma solidity ^0.8.30;\n\nimport { IERC20 } from \"@openzeppelin/contracts/token/ERC20/IERC20.sol\";\nimport { Ownable } from \"@openzeppelin/contracts/access/Ownable.sol\";\nimport { ProtocolTypes } from \"./interfaces/ProtocolTypes.sol\";\nimport { IGateway } from \"./interfaces/IGateway.sol\";\n\n/// @title KapanAuthorizationHelper\n/// @notice Standalone contract to generate authorization/deauthorization calls for KapanRouter\n/// @dev Separated from KapanRouter to stay under contract size limits\ncontract KapanAuthorizationHelper is Ownable {\n    bytes32 constant ROUTER_KEY = keccak256(abi.encode(\"router\"));\n    \n    error Unauthorized();\n\n    // Router instruction types (must match KapanRouter)\n    enum RouterInstructionType {\n        FlashLoan,\n        PullToken,\n        PushToken,\n        ToOutput,\n        Approve,\n        Split,\n        Add,\n        Subtract\n    }\n\n    // Flash loan providers (must match KapanRouter)\n    enum FlashLoanProvider {\n        BalancerV2,\n        BalancerV3,\n        Aave,\n        ZeroLend,\n        UniswapV3,\n        Morpho\n    }\n\n    struct RouterInstruction {\n        uint256 amount;\n        address token;\n        address user;\n        RouterInstructionType instructionType;\n    }\n\n    /// @dev Struct to hold authorization processing state\n    struct AuthState {\n        address[] tmpTargets;\n        bytes[] tmpData;\n        ProtocolTypes.Output[] outputs;\n        uint256 k;\n    }\n\n    address public immutable router;\n    mapping(string => IGateway) public gateways;\n\n    constructor(address _router, address _owner) Ownable(_owner) {\n        router = _router;\n    }\n\n    /// @notice Sync a gateway registration from the router\n    /// @dev Only callable by owner or router\n    function syncGateway(string calldata protocolName, address gateway) external {\n        if (msg.sender != owner() && msg.sender != router) revert Unauthorized();\n        gateways[protocolName] = IGateway(gateway);\n    }\n\n    /// @notice Generate authorization calls for a sequence of instructions\n    function authorizeInstructions(\n        ProtocolTypes.ProtocolInstruction[] calldata instructions,\n        address caller\n    ) external view returns (address[] memory targets, bytes[] memory data) {\n        AuthState memory state;\n        state.tmpTargets = new address[](instructions.length * 3);\n        state.tmpData = new bytes[](instructions.length * 3);\n        state.outputs = new ProtocolTypes.Output[](0);\n\n        for (uint256 i = 0; i < instructions.length; i++) {\n            state = _processAuthInstruction(instructions[i], caller, state, true);\n        }\n\n        return _compactAuthResults(state);\n    }\n\n    /// @notice Generate deauthorization calls for a sequence of instructions\n    function deauthorizeInstructions(\n        ProtocolTypes.ProtocolInstruction[] calldata instructions,\n        address caller\n    ) external view returns (address[] memory targets, bytes[] memory data) {\n        AuthState memory state;\n        state.tmpTargets = new address[](instructions.length * 3);\n        state.tmpData = new bytes[](instructions.length * 3);\n        state.outputs = new ProtocolTypes.Output[](0);\n\n        for (uint256 i = 0; i < instructions.length; i++) {\n            state = _processAuthInstruction(instructions[i], caller, state, false);\n        }\n\n        return _compactAuthResults(state);\n    }\n\n    function _processAuthInstruction(\n        ProtocolTypes.ProtocolInstruction calldata pi,\n        address caller,\n        AuthState memory state,\n        bool isAuth\n    ) private view returns (AuthState memory) {\n        if (keccak256(abi.encode(pi.protocolName)) == ROUTER_KEY) {\n            return _processRouterAuth(pi, caller, state, isAuth);\n        } else {\n            return _processGatewayAuth(pi, caller, state, isAuth);\n        }\n    }\n\n    function _processRouterAuth(\n        ProtocolTypes.ProtocolInstruction calldata pi,\n        address caller,\n        AuthState memory state,\n        bool isAuth\n    ) private view returns (AuthState memory) {\n        RouterInstruction memory r = abi.decode(pi.data, (RouterInstruction));\n        \n        if (r.instructionType == RouterInstructionType.PullToken) {\n            if (isAuth) {\n                (state.tmpTargets[state.k], state.tmpData[state.k]) = _getAuthForPullToken(pi.data, caller);\n            } else {\n                (state.tmpTargets[state.k], state.tmpData[state.k]) = _getDeauthForPullToken(pi.data, caller);\n            }\n        } else {\n            state.tmpTargets[state.k] = address(0);\n            state.tmpData[state.k] = bytes(\"\");\n        }\n        state.k++;\n        \n        state.outputs = _simulateRouterInstruction(pi, state.outputs);\n        return state;\n    }\n\n    function _processGatewayAuth(\n        ProtocolTypes.ProtocolInstruction calldata pi,\n        address caller,\n        AuthState memory state,\n        bool isAuth\n    ) private view returns (AuthState memory) {\n        IGateway gw = gateways[pi.protocolName];\n        if (address(gw) == address(0)) {\n            state.tmpTargets[state.k] = address(0);\n            state.tmpData[state.k] = bytes(\"\");\n            state.k++;\n            return state;\n        }\n\n        ProtocolTypes.LendingInstruction[] memory one = new ProtocolTypes.LendingInstruction[](1);\n        one[0] = abi.decode(pi.data, (ProtocolTypes.LendingInstruction));\n\n        if (isAuth) {\n            state = _handleGatewayAuthorize(gw, one, caller, state);\n        } else {\n            state = _handleGatewayDeauthorize(gw, one, caller, state);\n        }\n        return state;\n    }\n\n    function _handleGatewayAuthorize(\n        IGateway gw,\n        ProtocolTypes.LendingInstruction[] memory one,\n        address caller,\n        AuthState memory state\n    ) private view returns (AuthState memory) {\n        (address[] memory t, bytes[] memory d, ProtocolTypes.Output[] memory produced) = \n            gw.authorize(one, caller, state.outputs);\n\n        for (uint256 j = 0; j < t.length; j++) {\n            if (t[j] != address(0) && d[j].length > 0) {\n                state.tmpTargets[state.k] = t[j];\n                state.tmpData[state.k] = d[j];\n                state.k++;\n            }\n        }\n\n        if (produced.length > 0) {\n            state.outputs = _concatOutputs(state.outputs, produced);\n        }\n        return state;\n    }\n\n    function _handleGatewayDeauthorize(\n        IGateway gw,\n        ProtocolTypes.LendingInstruction[] memory one,\n        address caller,\n        AuthState memory state\n    ) private view returns (AuthState memory) {\n        (address[] memory t, bytes[] memory d) = gw.deauthorize(one, caller, state.outputs);\n        \n        for (uint256 j = 0; j < t.length; j++) {\n            state.tmpTargets[state.k] = t[j] != address(0) ? t[j] : address(0);\n            state.tmpData[state.k] = t[j] != address(0) ? d[j] : bytes(\"\");\n            state.k++;\n        }\n\n        // Update simulation state using authorize\n        (, , ProtocolTypes.Output[] memory produced) = gw.authorize(one, caller, state.outputs);\n        if (produced.length > 0) {\n            state.outputs = _concatOutputs(state.outputs, produced);\n        }\n        return state;\n    }\n\n    function _compactAuthResults(AuthState memory state) \n        private pure returns (address[] memory targets, bytes[] memory data) \n    {\n        targets = new address[](state.k);\n        data = new bytes[](state.k);\n        for (uint256 i = 0; i < state.k; i++) {\n            targets[i] = state.tmpTargets[i];\n            data[i] = state.tmpData[i];\n        }\n    }\n\n    // ============ Router Instruction Helpers ============\n\n    function _getAuthForPullToken(\n        bytes calldata data,\n        address caller\n    ) private view returns (address target, bytes memory callData) {\n        RouterInstruction memory r = abi.decode(data, (RouterInstruction));\n        if (r.user == caller) {\n            uint256 current = IERC20(r.token).allowance(caller, router);\n            if (current < r.amount) {\n                return (r.token, abi.encodeWithSelector(IERC20.approve.selector, router, r.amount));\n            }\n        }\n        return (address(0), bytes(\"\"));\n    }\n\n    function _getDeauthForPullToken(\n        bytes calldata data,\n        address caller\n    ) private view returns (address target, bytes memory callData) {\n        RouterInstruction memory r = abi.decode(data, (RouterInstruction));\n        if (r.user == caller) {\n            return (r.token, abi.encodeWithSelector(IERC20.approve.selector, router, 0));\n        }\n        return (address(0), bytes(\"\"));\n    }\n\n    function _simulateRouterInstruction(\n        ProtocolTypes.ProtocolInstruction calldata pi,\n        ProtocolTypes.Output[] memory outputs\n    ) private pure returns (ProtocolTypes.Output[] memory) {\n        RouterInstruction memory r = abi.decode(pi.data, (RouterInstruction));\n\n        if (r.instructionType == RouterInstructionType.PullToken) {\n            return _appendOutput(outputs, ProtocolTypes.Output({ token: r.token, amount: r.amount }));\n        } else if (r.instructionType == RouterInstructionType.PushToken) {\n            return _handlePushToken(pi.data, outputs);\n        } else if (r.instructionType == RouterInstructionType.ToOutput) {\n            return _appendOutput(outputs, ProtocolTypes.Output({ token: r.token, amount: r.amount }));\n        } else if (r.instructionType == RouterInstructionType.Approve) {\n            return _appendOutput(outputs, ProtocolTypes.Output({ token: address(0), amount: 0 }));\n        } else if (r.instructionType == RouterInstructionType.FlashLoan) {\n            return _handleFlashLoan(pi.data, outputs);\n        } else if (r.instructionType == RouterInstructionType.Split) {\n            return _handleSplit(pi.data, outputs);\n        } else if (r.instructionType == RouterInstructionType.Add) {\n            return _handleAdd(pi.data, outputs);\n        } else if (r.instructionType == RouterInstructionType.Subtract) {\n            return _handleSubtract(pi.data, outputs);\n        }\n        return outputs;\n    }\n\n    function _handlePushToken(\n        bytes calldata data,\n        ProtocolTypes.Output[] memory outputs\n    ) private pure returns (ProtocolTypes.Output[] memory) {\n        (, ProtocolTypes.InputPtr memory inputPtr) = abi.decode(data, (RouterInstruction, ProtocolTypes.InputPtr));\n        if (inputPtr.index < outputs.length) {\n            outputs[inputPtr.index] = ProtocolTypes.Output({ token: address(0), amount: 0 });\n        }\n        return outputs;\n    }\n\n    function _handleFlashLoan(\n        bytes calldata data,\n        ProtocolTypes.Output[] memory outputs\n    ) private pure returns (ProtocolTypes.Output[] memory) {\n        (, , ProtocolTypes.InputPtr memory inputPtr, ) = abi.decode(\n            data,\n            (RouterInstruction, FlashLoanProvider, ProtocolTypes.InputPtr, address)\n        );\n        if (inputPtr.index < outputs.length) {\n            ProtocolTypes.Output memory loanOut = outputs[inputPtr.index];\n            // 0.1% buffer for flash loan fees\n            loanOut.amount = (loanOut.amount * 1001) / 1000;\n            return _appendOutput(outputs, loanOut);\n        }\n        return _appendOutput(outputs, ProtocolTypes.Output({ token: address(0), amount: 0 }));\n    }\n\n    function _handleSplit(\n        bytes calldata data,\n        ProtocolTypes.Output[] memory outputs\n    ) private pure returns (ProtocolTypes.Output[] memory) {\n        (, ProtocolTypes.InputPtr memory inputPtr, uint256 bp) = abi.decode(\n            data,\n            (RouterInstruction, ProtocolTypes.InputPtr, uint256)\n        );\n        if (inputPtr.index < outputs.length) {\n            ProtocolTypes.Output memory orig = outputs[inputPtr.index];\n            uint256 feeAmount = (orig.amount * bp + 10000 - 1) / 10000;\n            if (feeAmount > orig.amount) feeAmount = orig.amount;\n            uint256 remainder = orig.amount - feeAmount;\n            outputs[inputPtr.index] = ProtocolTypes.Output({ token: address(0), amount: 0 });\n            outputs = _appendOutput(outputs, ProtocolTypes.Output({ token: orig.token, amount: feeAmount }));\n            return _appendOutput(outputs, ProtocolTypes.Output({ token: orig.token, amount: remainder }));\n        }\n        outputs = _appendOutput(outputs, ProtocolTypes.Output({ token: address(0), amount: 0 }));\n        return _appendOutput(outputs, ProtocolTypes.Output({ token: address(0), amount: 0 }));\n    }\n\n    function _handleAdd(\n        bytes calldata data,\n        ProtocolTypes.Output[] memory outputs\n    ) private pure returns (ProtocolTypes.Output[] memory) {\n        (, ProtocolTypes.InputPtr memory ptrA, ProtocolTypes.InputPtr memory ptrB) = abi.decode(\n            data,\n            (RouterInstruction, ProtocolTypes.InputPtr, ProtocolTypes.InputPtr)\n        );\n        if (ptrA.index < outputs.length && ptrB.index < outputs.length) {\n            ProtocolTypes.Output memory outA = outputs[ptrA.index];\n            ProtocolTypes.Output memory outB = outputs[ptrB.index];\n            uint256 total = outA.amount + outB.amount;\n            outputs[ptrA.index] = ProtocolTypes.Output({ token: address(0), amount: 0 });\n            outputs[ptrB.index] = ProtocolTypes.Output({ token: address(0), amount: 0 });\n            return _appendOutput(outputs, ProtocolTypes.Output({ token: outA.token, amount: total }));\n        }\n        return _appendOutput(outputs, ProtocolTypes.Output({ token: address(0), amount: 0 }));\n    }\n\n    function _handleSubtract(\n        bytes calldata data,\n        ProtocolTypes.Output[] memory outputs\n    ) private pure returns (ProtocolTypes.Output[] memory) {\n        (, ProtocolTypes.InputPtr memory ptrA, ProtocolTypes.InputPtr memory ptrB) = abi.decode(\n            data,\n            (RouterInstruction, ProtocolTypes.InputPtr, ProtocolTypes.InputPtr)\n        );\n        if (ptrA.index < outputs.length && ptrB.index < outputs.length) {\n            ProtocolTypes.Output memory outA = outputs[ptrA.index];\n            ProtocolTypes.Output memory outB = outputs[ptrB.index];\n            uint256 diff = outA.amount >= outB.amount ? outA.amount - outB.amount : 0;\n            outputs[ptrA.index] = ProtocolTypes.Output({ token: address(0), amount: 0 });\n            outputs[ptrB.index] = ProtocolTypes.Output({ token: address(0), amount: 0 });\n            return _appendOutput(outputs, ProtocolTypes.Output({ token: outA.token, amount: diff }));\n        }\n        return _appendOutput(outputs, ProtocolTypes.Output({ token: address(0), amount: 0 }));\n    }\n\n    function _appendOutput(\n        ProtocolTypes.Output[] memory current,\n        ProtocolTypes.Output memory item\n    ) private pure returns (ProtocolTypes.Output[] memory) {\n        ProtocolTypes.Output[] memory next = new ProtocolTypes.Output[](current.length + 1);\n        for (uint i = 0; i < current.length; i++) next[i] = current[i];\n        next[current.length] = item;\n        return next;\n    }\n\n    function _concatOutputs(\n        ProtocolTypes.Output[] memory current,\n        ProtocolTypes.Output[] memory items\n    ) private pure returns (ProtocolTypes.Output[] memory) {\n        ProtocolTypes.Output[] memory next = new ProtocolTypes.Output[](current.length + items.length);\n        for (uint i = 0; i < current.length; i++) next[i] = current[i];\n        for (uint j = 0; j < items.length; j++) next[current.length + j] = items[j];\n        return next;\n    }\n}\n"
    }
  },
  "settings": {
    "evmVersion": "cancun",
    "optimizer": {
      "enabled": true,
      "runs": 10
    },
    "outputSelection": {
      "*": {
        "*": [
          "abi",
          "evm.bytecode",
          "evm.deployedBytecode",
          "evm.methodIdentifiers",
          "metadata",
          "devdoc",
          "userdoc",
          "storageLayout",
          "evm.gasEstimates"
        ],
        "": [
          "ast"
        ]
      }
    },
    "metadata": {
      "useLiteralContent": true
    }
  }
}